LICENSE
s3_to_sftp/__init__.py
s3_to_sftp/logger.py
s3_to_sftp/secret-format.json
s3_to_sftp/transfer_file.py
s3_to_sftp/transfer_handler.py
s3_to_sftp/worker.py
s3_to_sftp-1.0.1.dist-info/LICENSE
s3_to_sftp-1.0.1.dist-info/WHEEL
s3_to_sftp-1.0.1.dist-info/METADATA
s3_to_sftp-1.0.1.dist-info/RECORD
