Metadata-Version: 2.1
Name: s3-to-sftp
Version: 1.0.1
Summary: S3 to SFTP application / watcher. Feeds from S3 to SQS notifications.
Keywords: compose-x,aws,sftp,docker,compose
Author: John Preston
Author-email: john@ews-network.net
Requires-Python: >=3.9,<4.0
Classifier: Development Status :: 4 - Beta
Classifier: Intended Audience :: Developers
Classifier: Intended Audience :: Information Technology
Classifier: Intended Audience :: System Administrators
Classifier: Natural Language :: English
Classifier: Programming Language :: Python :: 3
Classifier: Programming Language :: Python :: 3.10
Classifier: Programming Language :: Python :: 3.11
Classifier: Programming Language :: Python :: 3.9
Requires-Dist: aws-embedded-metrics (>=2.0,<3.0)
Requires-Dist: boto3 (>=1.24.22,<2.0.0)
Requires-Dist: compose-x-common (>=1.0.3,<2.0.0)
Requires-Dist: jsonschema (>=4,<5)
Requires-Dist: paramiko (>=2.11.0,<3.0.0)
